there_is_no_spoon/__init__.py
there_is_no_spoon/main.py
there_is_no_spoon/utils.py
there_is_no_spoon-1.0.12.dist-info/LICENSE
there_is_no_spoon-1.0.12.dist-info/METADATA
there_is_no_spoon-1.0.12.dist-info/WHEEL
there_is_no_spoon-1.0.12.dist-info/entry_points.txt
there_is_no_spoon-1.0.12.dist-info/top_level.txt
there_is_no_spoon-1.0.12.dist-info/RECORD
